bscscan/__init__.py
bscscan/client.py
bscscan/configs/__init__.py
bscscan/configs/stable.json
bscscan/core/__init__.py
bscscan/core/async_client.py
bscscan/core/base.py
bscscan/core/sync_client.py
bscscan/enums/__init__.py
bscscan/enums/actions_enum.py
bscscan/enums/fields_enum.py
bscscan/enums/modules_enum.py
bscscan/enums/tags_enum.py
bscscan/modules/__init__.py
bscscan/modules/accounts.py
bscscan/modules/blocks.py
bscscan/modules/contracts.py
bscscan/modules/logs.py
bscscan/modules/proxy.py
bscscan/modules/stats.py
bscscan/modules/tokens.py
bscscan/modules/transactions.py
bscscan/utils/__init__.py
bscscan/utils/conversions.py
bscscan/utils/parsing.py
bscscan_python_testnet-2.0.1.dist-info/LICENSE
bscscan_python_testnet-2.0.1.dist-info/METADATA
bscscan_python_testnet-2.0.1.dist-info/WHEEL
bscscan_python_testnet-2.0.1.dist-info/top_level.txt
bscscan_python_testnet-2.0.1.dist-info/RECORD
