Metadata-Version: 2.1
Name: bscscan-python-testnet
Version: 2.0.1
Summary: A python API for bscscan.com with support for BSC Testnet
Home-page: https://github.com/gabr1e11/bscscan-python
Author: Panagiotis-Christos Kotsias, Roberto Cano
Author-email: kotsias.pan@gmail.com, thesolidchain@gmail.com
License: MIT
Platform: UNKNOWN
Requires-Python: >=3.8
License-File: LICENSE
Requires-Dist: aiohttp
Requires-Dist: requests
